{
  "collection": "setting",
  "slug": "navigation",
  "title": "Tiere",
  "links": [
    {
      "type": "link",
      "text": "Home",
      "href": "/"
    },
    {
      "type": "link",
      "text": "Über mich",
      "href": "/ueber-mich"
    },
    {
      "type": "link",
      "text": "Kala Heilarbeit",
      "href": "/kala-heilarbeit"
    },
    {
      "type": "link",
      "text": "Ausbildung",
      "href": "/ausbildung"
    },
    {
      "type": "link",
      "text": "Yoga",
      "href": "/seminar/yoga"
    },
    {
      "type": "link",
      "text": "Heilsame Seminare",
      "href": "/heilsame-seminare"
    },
    {
      "type": "link",
      "text": "Blog",
      "href": "/blog"
    },
    {
      "type": "link",
      "text": "Kontakt",
      "href": "/kontakt"
    }
  ]
}